pysuperconductor/__init__.py
pysuperconductor/meta.py
pysuperconductor/os_gap_calc.py
pysuperconductor-0.1.1.dist-info/WHEEL
pysuperconductor-0.1.1.dist-info/METADATA
pysuperconductor-0.1.1.dist-info/RECORD
