Metadata-Version: 2.1
Name: pysuperconductor
Version: 0.1.1
Summary: 
Author: Deepak
Author-email: dmallubhotla+github@gmail.com
Requires-Python: >=3.8,<4.0
Classifier: Programming Language :: Python :: 3
Classifier: Programming Language :: Python :: 3.8
Classifier: Programming Language :: Python :: 3.9
Requires-Dist: numpy (==1.19.3)
Requires-Dist: scipy (>=1.5.4,<2.0.0)
